uncurl/__init__.py
uncurl/api.py
uncurl/bin.py
uncurl_pk-0.0.4.dist-info/LICENSE
uncurl_pk-0.0.4.dist-info/METADATA
uncurl_pk-0.0.4.dist-info/WHEEL
uncurl_pk-0.0.4.dist-info/entry_points.txt
uncurl_pk-0.0.4.dist-info/top_level.txt
uncurl_pk-0.0.4.dist-info/RECORD
